eleflow/__builder__.py
eleflow/__init__.py
eleflow/connector/__init__.py
eleflow/connector/azure_cosmosdb/__init__.py
eleflow/connector/azure_cosmosdb/cosmosdb_connection.py
eleflow/connector/azure_cosmosdb/cosmosdb_document.py
eleflow/connector/azure_cosmosdb/cosmosdb_service_client.py
eleflow/connector/google_sheet/__init__.py
eleflow/connector/google_sheet/google_sheet.py
eleflow/connector/google_sheet/google_sheet_connection.py
eleflow/connector/google_sheet/google_sheet_service_client.py
eleflow/connector/google_sheet/google_spreadsheet.py
eleflow/connector/rest_api/__init__.py
eleflow/connector/rest_api/rest_api_connection.py
eleflow/connector/rest_api/rest_base.py
eleflow/connector/rest_api/spark_rest_response.py
eleflow/connector/sql_db/__init__.py
eleflow/connector/sql_db/sql_db.py
eleflow/converter/__init__.py
eleflow/converter/google_sheets_dataframe_converter.py
eleflow/converter/json_dataframe_converter.py
eleflow/integrator/__init__.py
eleflow/integrator/pipe_drive/__init__.py
eleflow/integrator/pipe_drive/_pipe_drive_connection.py
eleflow/integrator/pipe_drive/_pipe_drive_service_client.py
eleflow/integrator/pipe_drive/services/__init__.py
eleflow/integrator/pipe_drive/services/_pipe_drive_activities.py
eleflow/integrator/pipe_drive/services/_pipe_drive_activity_fields.py
eleflow/integrator/pipe_drive/services/_pipe_drive_activity_types.py
eleflow/integrator/pipe_drive/services/_pipe_drive_call_logs.py
eleflow/integrator/pipe_drive/services/_pipe_drive_currencies.py
eleflow/integrator/pipe_drive/services/_pipe_drive_deals.py
eleflow/integrator/pipe_drive/services/_pipe_drive_deals_fields.py
eleflow/integrator/pipe_drive/services/_pipe_drive_files.py
eleflow/integrator/pipe_drive/services/_pipe_drive_filters.py
eleflow/integrator/pipe_drive/services/_pipe_drive_global_messages.py
eleflow/integrator/pipe_drive/services/_pipe_drive_goals.py
eleflow/integrator/pipe_drive/services/_pipe_drive_item_search.py
pyspark_connectors-0.3.0.dist-info/LICENSE
pyspark_connectors-0.3.0.dist-info/METADATA
pyspark_connectors-0.3.0.dist-info/WHEEL
pyspark_connectors-0.3.0.dist-info/top_level.txt
pyspark_connectors-0.3.0.dist-info/RECORD
