Metadata-Version: 2.1
Name: pyspark-connectors
Version: 0.3.0
Summary: The easy and quickly way to connect and integrate the Spark project with many others data sources.
Home-page: https://github.com/eleflow/pyspark-connectors/
Author: Eleflow BigData
Author-email: caio.araujo@eleflow.com.br
License: MIT
Keywords: pyspark databricks integrator connector cosmosdb sql nosql sqlserver oracle mysql postgres mariadb pipedrive activecampaign googlesheet restapi
Platform: UNKNOWN
Requires-Python: >=3.8
License-File: LICENSE
Requires-Dist: azure-cosmos (==4.2.0)
Requires-Dist: google-api-python-client (==2.47.0)
Requires-Dist: google-auth-httplib2 (==0.1.0)
Requires-Dist: google-auth-oauthlib (==0.5.1)
Requires-Dist: pyspark (==3.2.1)
Requires-Dist: requests (==2.27.1)
Requires-Dist: unidecode
